LICENSE
MANIFEST.in
README.md
pyproject.toml
setup.cfg
setup.py
docassemble.ILAO.egg-info/PKG-INFO
docassemble.ILAO.egg-info/SOURCES.txt
docassemble.ILAO.egg-info/dependency_links.txt
docassemble.ILAO.egg-info/not-zip-safe
docassemble.ILAO.egg-info/top_level.txt
docassemble/ILAO/__init__.py
docassemble/ILAO/docs_list.py
docassemble/ILAO/ilao_easy_forms_database.py
docassemble/ILAO/ilao_suffix.py
docassemble/ILAO/ilao_tools.py
docassemble/ILAO/toolbox.py
docassemble/ILAO/data/questions/default-home.yml
docassemble/ILAO/data/questions/feedback.yml
docassemble/ILAO/data/questions/ilao-interview-framework.yml
docassemble/ILAO/data/questions/ilao_interview_list.yml
docassemble/ILAO/data/questions/shared-basic-questions.yml
docassemble/ILAO/data/sources/README.md
docassemble/ILAO/data/sources/il_courts.xlsx
docassemble/ILAO/data/sources/ilao-words.yml
docassemble/ILAO/data/sources/ilao_docassemble_easy_forms.xlsx
docassemble/ILAO/data/static/README.md
docassemble/ILAO/data/static/android-chrome-192x192.png
docassemble/ILAO/data/static/android-chrome-512x512.png
docassemble/ILAO/data/static/apple-touch-icon.png
docassemble/ILAO/data/static/browserconfig.xml
docassemble/ILAO/data/static/case_number.png
docassemble/ILAO/data/static/favicon-16x16.png
docassemble/ILAO/data/static/favicon-32x32.png
docassemble/ILAO/data/static/favicon.ico
docassemble/ILAO/data/static/force_lightmode.js
docassemble/ILAO/data/static/ilao.logo.21.svg
docassemble/ILAO/data/static/ilao.logo.new.svg
docassemble/ILAO/data/static/ilao.logo.noname.25.png
docassemble/ILAO/data/static/ilao.logo.svg
docassemble/ILAO/data/static/ilao_docs_table.css
docassemble/ILAO/data/static/ilao_theme.css
docassemble/ILAO/data/static/ilao_theme_2.css
docassemble/ILAO/data/static/logo1.png
docassemble/ILAO/data/static/logo1.svg
docassemble/ILAO/data/static/logo2.svg
docassemble/ILAO/data/static/logo_gray_26.svg
docassemble/ILAO/data/static/logo_white_26.svg
docassemble/ILAO/data/static/logo_white_30.svg
docassemble/ILAO/data/static/manifest.json
docassemble/ILAO/data/static/mstile-150x150.png
docassemble/ILAO/data/static/safari-pinned-tab.svg
docassemble/ILAO/data/templates/README.md