Metadata-Version: 2.4
Name: docassemble.ILAO
Version: 1.1.10
Summary: A docassemble extension.
Home-page: https://docassemble.org
Author: Matt Newsted
Author-email: mnewsted@illinoislegalaid.org
License: The MIT License (MIT)
License-File: LICENSE
Dynamic: author
Dynamic: author-email
Dynamic: description
Dynamic: description-content-type
Dynamic: home-page
Dynamic: license
Dynamic: license-file
Dynamic: summary
